{
  "id": "mcp-server-azure-devops",
  "name": "mcp-server-azure-devops ",
  "description": "Azure DevOps integration for repository management, work items, and pipelines.",
  "links":
    {
      "artifacts": "https://hub.docker.com/r/acuvity/mcp-server-azure-devops",
      "application": "https://github.com/Tiberriver256/mcp-server-azure-devops"
    },
  "tags": ["integration","research","development"],
  "official": false,
  "scope": "remote",
  "mutitenant": true,
  "runtime": "node",
  "version": "0.1.36",
  "requiresConfiguration": true,
  "requiresStorage": false,
  "rating": "C",
  "resources": {
    "tools": 30,
    "prompts": 0,
    "resources": 0,
    "resourcesTemplates": 0
  }
}
