{
  "id": "mcp-server-sequential-thinking",
  "icon": "https://raw.githubusercontent.com/modelcontextprotocol/docs/refs/heads/main/favicon.svg",
  "name": "mcp-server-sequential-thinking",
  "description": "MCP server for sequential thinking and problem solving",
  "links":
    {
      "artifacts": "https://hub.docker.com/r/acuvity/mcp-server-sequential-thinking",
      "application": "https://modelcontextprotocol.io"
    },
  "tags": ["development","automation"],
  "official": false,
  "scope": "standalone",
  "mutitenant": false,
  "runtime": "node",
  "version": "2025.12.18",
  "requiresConfiguration": false,
  "requiresStorage": false,
  "rating": {"hash":"a051033c7161ff06eb87ebfdd158e8483cf1deb84a374f28ca1022687fe41fad","reason":"The tool has a clear, descriptive name and comprehensive documentation covering functionality, usage context, and key features. The description is thorough (perhaps overly detailed) and the parameter explanations are complete with purpose and constraints. However, the description is quite lengthy and could be more concise, and some parameter descriptions could be clearer about their specific roles in the thinking process.","score":"B"},
  "resources": {
    "tools": 1,
    "prompts": 0,
    "resources": 0,
    "resourcesTemplates": 0
  }
}
